[{"id": 1271993037, "round": "Regular Season - 14", "date": "2026-07-18T14:00:00.000Z", "country": {"code": "NO", "name": "Norway", "logo": "https://highlightly.net/soccer/images/countries/NO.svg"}, "state": {"clock": 90, "score": {"current": "2 - 1", "penalties": null}, "description": "Finished"}, "awayTeam": {"id": 1824477, "logo": "https://highlightly.net/soccer/images/teams/1824477.png", "name": "KFUM Oslo"}, "homeTeam": {"id": 273955, "logo": "https://highlightly.net/soccer/images/teams/273955.png", "name": "Lillestr\u00f8m"}, "league": {"id": 88437, "logo": "https://highlightly.net/soccer/images/leagues/88437.png", "name": "Eliteserien", "season": 2026}}, {"id": 1271986229, "round": "Regular Season - 13", "date": "2026-07-12T12:30:00.000Z", "country": {"code": "NO", "name": "Norway", "logo": "https://highlightly.net/soccer/images/countries/NO.svg"}, "state": {"clock": 90, "score": {"current": "0 - 2", "penalties": null}, "description": "Finished"}, "awayTeam": {"id": 279061, "logo": "https://highlightly.net/soccer/images/teams/279061.png", "name": "Bod\u00f8/Glimt"}, "homeTeam": {"id": 1824477, "logo": "https://highlightly.net/soccer/images/teams/1824477.png", "name": "KFUM Oslo"}, "league": {"id": 88437, "logo": "https://highlightly.net/soccer/images/leagues/88437.png", "name": "Eliteserien", "season": 2026}}, {"id": 1347274199, "round": "Club Friendly", "date": "2026-07-04T12:00:00.000Z", "country": {"code": "World", "name": "World", "logo": "https://highlightly.net/soccer/images/countries/World.png"}, "state": {"clock": 90, "score": {"current": "2 - 0", "penalties": null}, "description": "Finished"}, "awayTeam": {"id": 1824477, "logo": "https://highlightly.net/soccer/images/teams/1824477.png", "name": "KFUM Oslo"}, "homeTeam": {"id": 340333, "logo": "https://highlightly.net/soccer/images/teams/340333.png", "name": "Vendsyssel FF"}, "league": {"id": 568401, "logo": "https://highlightly.net/soccer/images/leagues/568401.png", "name": "Friendlies Clubs", "season": 2026}}, {"id": 1322875178, "round": "Club Friendlies", "date": "2026-06-21T16:00:00.000Z", "country": {"code": "World", "name": "World", "logo": "https://highlightly.net/soccer/images/countries/World.png"}, "state": {"clock": 90, "score": {"current": "5 - 1", "penalties": null}, "description": "Finished"}, "awayTeam": {"id": 1824477, "logo": "https://highlightly.net/soccer/images/teams/1824477.png", "name": "KFUM Oslo"}, "homeTeam": {"id": 280763, "logo": "https://highlightly.net/soccer/images/teams/280763.png", "name": "Molde"}, "league": {"id": 568401, "logo": "https://highlightly.net/soccer/images/leagues/568401.png", "name": "Friendlies Clubs", "season": 2026}}, {"id": 1271972613, "round": "Regular Season - 11", "date": "2026-05-29T17:00:00.000Z", "country": {"code": "NO", "name": "Norway", "logo": "https://highlightly.net/soccer/images/countries/NO.svg"}, "state": {"clock": 90, "score": {"current": "0 - 0", "penalties": null}, "description": "Finished"}, "awayTeam": {"id": 277359, "logo": "https://highlightly.net/soccer/images/teams/277359.png", "name": "Troms\u00f8 IL"}, "homeTeam": {"id": 1824477, "logo": "https://highlightly.net/soccer/images/teams/1824477.png", "name": "KFUM Oslo"}, "league": {"id": 88437, "logo": "https://highlightly.net/soccer/images/leagues/88437.png", "name": "Eliteserien", "season": 2026}}]